mediafiredl/MediafireDL.py
mediafiredl/__init__.py
mediafiredl-0.0.2.dist-info/LICENSE
mediafiredl-0.0.2.dist-info/METADATA
mediafiredl-0.0.2.dist-info/WHEEL
mediafiredl-0.0.2.dist-info/top_level.txt
mediafiredl-0.0.2.dist-info/RECORD
