Metadata-Version: 2.1
Name: mediafiredl
Version: 0.0.2
Summary: MediafireDL is an automation tool to download files from mediafire without having to do any extra steps.
Home-page: https://github.com/Gann4/mediafiredl
Author: Santiago Ariel Mansilla
Author-email: santiago_ariel_mansilla@hotmail.com
License: UNKNOWN
Platform: UNKNOWN
Classifier: Programming Language :: Python :: 3
Classifier: License :: OSI Approved :: MIT License
Classifier: Operating System :: OS Independent
Requires-Python: >=3.8
License-File: LICENSE
Requires-Dist: bs4
Requires-Dist: requests
